secbench/processing/__init__.py
secbench/processing/_native.py
secbench/processing/_network.py
secbench/processing/helpers.py
secbench/processing/metrics.py
secbench/processing/models.py
secbench/processing/profiled.py
secbench/processing/signal.py
secbench/processing/crypto/__init__.py
secbench/processing/crypto/aes.py
secbench/processing/crypto/crc8.py
secbench/processing/crypto/keccak.py
secbench/processing/crypto/pcg32.py
secbench/processing/oracles/__init__.py
secbench/processing/oracles/sliding.py
secbench_processing-2.12.0.dist-info/licenses/LICENSE
tests/test_aes.py
tests/test_dsp.py
tests/test_helpers.py
tests/test_keccak.py
tests/test_metrics.py
tests/test_models.py
tests/test_pcg32.py
tests/test_profiled.py
tests/test_signal.py
secbench_processing-2.12.0.dist-info/METADATA
secbench_processing-2.12.0.dist-info/WHEEL
secbench_processing-2.12.0.dist-info/top_level.txt
secbench_processing-2.12.0.dist-info/RECORD
