Metadata-Version: 2.4
Name: secbench-processing
Version: 2.12.0
Summary: Secbench algorithms for side-channel analysis
Author-email: Secbench team <support@secbench.fr>
License: 
Project-URL: Homepage, https://doc.secbench.fr
Project-URL: Bug Reports, https://github.com/CEA-Leti/secbench/issues
Project-URL: Source, https://github.com/CEA-Leti/secbench
Classifier: Programming Language :: Python :: 3
Classifier: Programming Language :: Python :: 3 :: Only
Classifier: Programming Language :: Python :: 3.10
Classifier: Programming Language :: Python :: 3.11
Classifier: Programming Language :: Python :: 3.12
Classifier: Programming Language :: Python :: 3.13
Classifier: Topic :: Security
Classifier: Topic :: Scientific/Engineering
Classifier: Intended Audience :: Developers
Classifier: Intended Audience :: Science/Research
Classifier: License :: OSI Approved :: CEA CNRS Inria Logiciel Libre License, version 2.1 (CeCILL-2.1)
Requires-Python: >=3.10
License-File: LICENSE
Requires-Dist: numpy>=1.21
Requires-Dist: scipy>=1.4.1
Requires-Dist: scikit-learn>=1.0.2
Requires-Dist: lttbc>=0.2
Requires-Dist: typing-extensions>=4.0.0
Requires-Dist: pandas>=2.0
Provides-Extra: mpl
Requires-Dist: matplotlib>=3.5; extra == "mpl"
Dynamic: license-file
